Metadata-Version: 2.1
Name: django-installed-apps-command
Version: 2020.7.1
Summary: prints settings.INSTALLED_APPS
Home-page: https://github.com/andrewp-as-is/django-installed-apps-command.py
License: Unlicense
Keywords: django
Platform: UNKNOWN
Classifier: Framework :: Django
Classifier: License :: Public Domain
Classifier: Operating System :: OS Independent
Classifier: Programming Language :: Python :: 3
